discord_mcp_agent/__init__.py
discord_mcp_agent/server.py
discord_mcp_agent-1.0.0.dist-info/METADATA
discord_mcp_agent-1.0.0.dist-info/WHEEL
discord_mcp_agent-1.0.0.dist-info/entry_points.txt
discord_mcp_agent-1.0.0.dist-info/licenses/LICENSE
discord_mcp_agent-1.0.0.dist-info/RECORD
