Metadata-Version: 2.4
Name: discord-mcp-agent
Version: 1.0.0
Summary: MCP server for Discord-based AI agent-user communication. Enables AI agents to communicate with users through Discord.
Project-URL: Homepage, https://github.com/zebbern/discord-mcp-agent
Project-URL: Repository, https://github.com/zebbern/discord-mcp-agent
Project-URL: Documentation, https://github.com/zebbern/discord-mcp-agent#readme
Author: zebbern
License-Expression: MIT
License-File: LICENSE
Keywords: agent-communication,ai-agent,discord,discord-bot,mcp,mcp-server,model-context-protocol
Classifier: Development Status :: 4 - Beta
Classifier: Intended Audience :: Developers
Classifier: License :: OSI Approved :: MIT License
Classifier: Programming Language :: Python :: 3
Classifier: Programming Language :: Python :: 3.10
Classifier: Programming Language :: Python :: 3.11
Classifier: Programming Language :: Python :: 3.12
Classifier: Topic :: Communications :: Chat
Classifier: Topic :: Software Development :: Libraries :: Python Modules
Requires-Python: >=3.10
Requires-Dist: aiohttp>=3.8.0
Requires-Dist: discord-py>=2.0.0
Requires-Dist: mcp>=1.0.0
Requires-Dist: pydantic>=2.0.0
Provides-Extra: dev
Requires-Dist: pytest-asyncio>=0.21.0; extra == 'dev'
Requires-Dist: pytest>=7.0.0; extra == 'dev'
Provides-Extra: screenshot
Requires-Dist: pillow>=10.0.0; extra == 'screenshot'
